pyesytime/__init__.py
pyesytime-2022.3.dist-info/LICENSE
pyesytime-2022.3.dist-info/METADATA
pyesytime-2022.3.dist-info/WHEEL
pyesytime-2022.3.dist-info/top_level.txt
pyesytime-2022.3.dist-info/RECORD
