Metadata-Version: 2.1
Name: pyesytime
Version: 2022.3
Summary: A module to make time easier
Author: SunnyLi
Author-email: 5327136@qq.com
License: UNKNOWN
Platform: UNKNOWN
Classifier: Programming Language :: Python :: 3
Classifier: License :: OSI Approved :: MIT License
Classifier: Operating System :: OS Independent
Requires-Python: >=3
License-File: LICENSE
